MANIFEST.in
README.md
my_module.py
requirements.txt
setup.py
standalone.txt
MarkdownPostgresArchive.egg-info/PKG-INFO
MarkdownPostgresArchive.egg-info/SOURCES.txt
MarkdownPostgresArchive.egg-info/dependency_links.txt
MarkdownPostgresArchive.egg-info/requires.txt
MarkdownPostgresArchive.egg-info/top_level.txt
markdownPostgresArchive/ArchiveDatabaseConnection.py
markdownPostgresArchive/ArchivePage.py
markdownPostgresArchive/DisplayHistory.py
markdownPostgresArchive/MDArchive.py
markdownPostgresArchive/MDArchiveSetup.py
markdownPostgresArchive/RestorePage.py
markdownPostgresArchive/__init__.py