Metadata-Version: 1.1
Name: MarkdownPostgresArchive
Version: 0.1.14
Summary: Stores and/or retrieves data of a markdown file in and out of a Postgresql database
Home-page: UNKNOWN
Author: UNKNOWN
Author-email: UNKNOWN
License: UNKNOWN
Platform: UNKNOWN
Classifier: Development Status :: 3 - Alpha
Classifier: Intended Audience :: Developers
Classifier: Programming Language :: Python :: 2.7
